energyusage/RAPLFile.py
energyusage/__init__.py
energyusage/convert.py
energyusage/evaluate.py
energyusage/locate.py
energyusage/raw_to_json.py
energyusage/report.py
energyusage/utils.py
energyusage/data/README.md
energyusage/data/csv/egrid_emissions_2016.csv
energyusage/data/csv/egrid_resource_mix_2016.csv
energyusage/data/csv/emissions-us.csv
energyusage/data/csv/energy-mix-intl.csv
energyusage/data/csv/energy-mix-us.csv
energyusage/data/json/energy-mix-intl_2016.json
energyusage/data/json/energy-mix-us_2016.json
energyusage/data/json/us-emissions_2016.json
energyusage-0.0.14.dist-info/AUTHORS.txt
energyusage-0.0.14.dist-info/LICENSE.txt
energyusage-0.0.14.dist-info/METADATA
energyusage-0.0.14.dist-info/WHEEL
energyusage-0.0.14.dist-info/top_level.txt
energyusage-0.0.14.dist-info/RECORD
