Metadata-Version: 2.1
Name: energyusage
Version: 0.0.14
Summary: Measuring the environmental impact of computation
Home-page: https://github.com/responsibleproblemsolving/energy-usage
Author: Sorelle Friedler, Kadan Lottick, Silvia Susai
Author-email: sorelle@cs.haverford.edu
License: Apache 2.0
Platform: UNKNOWN
Classifier: Programming Language :: Python :: 3
Classifier: License :: OSI Approved :: Apache Software License
Classifier: Operating System :: OS Independent
